pdfathom/__main__.py
pdfathom/arguments.py
pdfathom/config.py
pdfathom/db.py
pdfathom/repl.py
pdfathom-0.1.4.dist-info/LICENSE
pdfathom-0.1.4.dist-info/METADATA
pdfathom-0.1.4.dist-info/WHEEL
pdfathom-0.1.4.dist-info/entry_points.txt
pdfathom-0.1.4.dist-info/RECORD
