Metadata-Version: 2.1
Name: pdfathom
Version: 0.1.4
Summary: Query PDFs in natural language from the command-line
License: CC0-1.0
Author: Liam
Author-email: liam@scalzulli.com
Requires-Python: >=3.8,<4.0
Classifier: License :: CC0 1.0 Universal (CC0 1.0) Public Domain Dedication
Classifier: Programming Language :: Python :: 3
Classifier: Programming Language :: Python :: 3.8
Classifier: Programming Language :: Python :: 3.9
Classifier: Programming Language :: Python :: 3.10
Classifier: Programming Language :: Python :: 3.11
Requires-Dist: chromadb (>=0.3.21,<0.4.0)
Requires-Dist: langchain (>=0.0.144,<0.0.145)
Requires-Dist: openai (>=0.27.4,<0.28.0)
Requires-Dist: pypdf (>=3.8.0,<4.0.0)
Requires-Dist: rich (>=13.3.4,<14.0.0)
Requires-Dist: tiktoken (>=0.3.3,<0.4.0)
